{
  "id": "62471638-c725-4de4-ab4f-df5ca717071c",
  "deletedDateTime": null,
  "accountEnabled": true,
  "alternativeNames": [],
  "appDisplayName": "MS-PIM",
  "appDescription": null,
  "appId": "01fc33a7-78ba-4d2f-a4b7-768e336e890e",
  "applicationTemplateId": null,
  "appOwnerOrganizationId": "f8cdef31-a31e-4b4a-93e4-5f571e91255a",
  "appRoleAssignmentRequired": false,
  "createdDateTime": "2025-09-20T16:23:27Z",
  "description": null,
  "disabledByMicrosoftStatus": null,
  "displayName": "MS-PIM",
  "homepage": null,
  "loginUrl": null,
  "logoutUrl": null,
  "notes": null,
  "notificationEmailAddresses": [],
  "preferredSingleSignOnMode": null,
  "preferredTokenSigningKeyThumbprint": null,
  "replyUrls": [],
  "servicePrincipalNames": [
    "01fc33a7-78ba-4d2f-a4b7-768e336e890e",
    "https://api.aadr.mspim.azure.com/",
    "https://api.azrbac.mspim.azure.com/",
    "https://mspim.onmicrosoft.com/",
    "https://canaryapi.azrbac.mspim.azure.com/"
  ],
  "servicePrincipalType": "Application",
  "signInAudience": "AzureADMultipleOrgs",
  "tags": [],
  "tokenEncryptionKeyId": null,
  "samlSingleSignOnSettings": null,
  "addIns": [],
  "appRoles": [],
  "info": {
    "logoUrl": null,
    "marketingUrl": null,
    "privacyStatementUrl": null,
    "supportUrl": null,
    "termsOfServiceUrl": null
  },
  "keyCredentials": [],
  "oauth2PermissionScopes": [],
  "passwordCredentials": [],
  "resourceSpecificApplicationPermissions": [],
  "verifiedPublisher": {
    "displayName": "Microsoft Corporation",
    "verifiedPublisherId": "5206095",
    "addedDateTime": "2025-08-21T17:19:01Z"
  },
  "@odata.context": "https://graph.microsoft.com/v1.0/$metadata#servicePrincipals/$entity"
}
